atxm/__init__.py
atxm/exceptions.py
atxm/logging.py
atxm/machine.py
atxm/main.py
atxm/strategies.py
atxm/tracker.py
atxm/tx.py
atxm/utils.py
atxm-0.5.0.dist-info/LICENSE
atxm-0.5.0.dist-info/METADATA
atxm-0.5.0.dist-info/WHEEL
atxm-0.5.0.dist-info/top_level.txt
atxm-0.5.0.dist-info/RECORD
