Metadata-Version: 2.1
Name: atxm
Version: 0.5.0
Summary: Automatic Transaction Machine (ATxM) for Ethereum
Author-email: NuCypher <devs@nucypher.com>
License: GNU AFFERO GENERAL PUBLIC LICENSE
Project-URL: Homepage, https://github.com/nucypher/atxm
Project-URL: Issues, https://github.com/nucypher/atxm/issues
Classifier: Programming Language :: Python :: 3 :: Only
Classifier: Programming Language :: Python :: 3.9
Classifier: Programming Language :: Python :: 3.10
Classifier: Programming Language :: Python :: 3.11
Classifier: Programming Language :: Python :: 3.12
Classifier: Topic :: Software Development :: Libraries :: Python Modules
Classifier: Intended Audience :: Developers
Classifier: Development Status :: 3 - Alpha
Classifier: Natural Language :: English
Classifier: Typing :: Typed
Classifier: Operating System :: OS Independent
Classifier: License :: OSI Approved :: GNU Affero General Public License v3 or later (AGPLv3+)
Requires-Python: >=3.9
License-File: LICENSE
